octo_pipeline_python/backends/snyk/__init__.py
octo_pipeline_python/backends/snyk/snyk_backend.py
octo_pipeline_python/backends/snyk/actions/__init__.py
octo_pipeline_python/backends/snyk/actions/snyk_code_checks.py
octo_pipeline_python/backends/snyk/actions/snyk_iac_checks.py
octo_pipeline_python/backends/snyk/actions/snyk_security_checks.py
octo_pipeline_python/backends/snyk/models/__init__.py
octo_pipeline_python/backends/snyk/models/snyk_model.py
octo_pipeline_backend_snyk_python-1.3.2.dist-info/LICENSE.txt
octo_pipeline_backend_snyk_python-1.3.2.dist-info/METADATA
octo_pipeline_backend_snyk_python-1.3.2.dist-info/README.md
octo_pipeline_backend_snyk_python-1.3.2.dist-info/WHEEL
octo_pipeline_backend_snyk_python-1.3.2.dist-info/top_level.txt
octo_pipeline_backend_snyk_python-1.3.2.dist-info/RECORD
